terrascript/core/__init__.py
terrascript/core/ast/__init__.py
terrascript/core/ast/argument.py
terrascript/core/ast/array.py
terrascript/core/ast/attribute.py
terrascript/core/ast/base.py
terrascript/core/ast/boolean.py
terrascript/core/ast/data.py
terrascript/core/ast/map.py
terrascript/core/ast/object.py
terrascript/core/ast/output.py
terrascript/core/ast/provider.py
terrascript/core/ast/resource.py
terrascript/core/ast/terraform.py
terrascript/core/ast/value.py
terrascript/core/cli.py
terrascript/core/cmd.py
terrascript/core/context.py
terrascript/core/generate.py
terrascript/core/lang/__init__.py
terrascript/core/lang/argument.py
terrascript/core/lang/attribute.py
terrascript/core/lang/block.py
terrascript/core/lang/data.py
terrascript/core/lang/decorators.py
terrascript/core/lang/decorators.pyi
terrascript/core/lang/output.py
terrascript/core/lang/provider.py
terrascript/core/lang/resource.py
terrascript/core/lang/terraform.py
terrascript/core/lang/types.py
terrascript/core/terraform/__init__.py
terrascript/core/terraform/backend/__init__.py
terrascript/core/terraform/backend/local.py
terrascript/core/terraform/backend/remote.py
terrascript/core/terraform/backend/s3.py
terrascript/core/terraform/provider.py
terrascript/core/terraform/settings.py
terrascript_core-1.0.7.dist-info/LICENSE.txt
terrascript_core-1.0.7.dist-info/METADATA
terrascript_core-1.0.7.dist-info/WHEEL
terrascript_core-1.0.7.dist-info/entry_points.txt
terrascript_core-1.0.7.dist-info/RECORD
