Metadata-Version: 2.1
Name: terrascript-core
Version: 1.0.7
Summary: Terrasript core Python SDK
Author: csylaios
Author-email: chris.sylaios@gmail.com
Requires-Python: >=3.10
Classifier: Programming Language :: Python :: 3
Classifier: Programming Language :: Python :: 3.10
Classifier: Programming Language :: Python :: 3.11
Requires-Dist: attrs (>=22.2.0,<23.0.0)
Requires-Dist: cattrs (>=22.2.0,<23.0.0)
Requires-Dist: click (>=8.1.3,<9.0.0)
Requires-Dist: command-runner (>=1.5.0,<2.0.0)
Requires-Dist: pybars3 (>=0.9.7,<0.10.0)
Requires-Dist: pydash (>=6.0.2,<7.0.0)
Requires-Dist: pytest-asyncio (>=0.16.0,<0.17.0)
